LICENSE
README.md
nautobot_ssot_servicenow/__init__.py
nautobot_ssot_servicenow/data/mappings.yaml
nautobot_ssot_servicenow/diffsync/__init__.py
nautobot_ssot_servicenow/diffsync/adapter_nautobot.py
nautobot_ssot_servicenow/diffsync/adapter_servicenow.py
nautobot_ssot_servicenow/diffsync/models.py
nautobot_ssot_servicenow/forms.py
nautobot_ssot_servicenow/jobs.py
nautobot_ssot_servicenow/migrations/0001_initial.py
nautobot_ssot_servicenow/migrations/__init__.py
nautobot_ssot_servicenow/models.py
nautobot_ssot_servicenow/servicenow.py
nautobot_ssot_servicenow/signals.py
nautobot_ssot_servicenow/static/nautobot_ssot_servicenow/ServiceNow_logo.svg
nautobot_ssot_servicenow/templates/nautobot_ssot_servicenow/config.html
nautobot_ssot_servicenow/tests/__init__.py
nautobot_ssot_servicenow/tests/test_adapter_nautobot.py
nautobot_ssot_servicenow/tests/test_adapter_servicenow.py
nautobot_ssot_servicenow/tests/test_basic.py
nautobot_ssot_servicenow/tests/test_jobs.py
nautobot_ssot_servicenow/third_party/pysnow/__init__.py
nautobot_ssot_servicenow/third_party/pysnow/attachment.py
nautobot_ssot_servicenow/third_party/pysnow/client.py
nautobot_ssot_servicenow/third_party/pysnow/criterion.py
nautobot_ssot_servicenow/third_party/pysnow/enums.py
nautobot_ssot_servicenow/third_party/pysnow/exceptions.py
nautobot_ssot_servicenow/third_party/pysnow/legacy_exceptions.py
nautobot_ssot_servicenow/third_party/pysnow/legacy_request.py
nautobot_ssot_servicenow/third_party/pysnow/oauth_client.py
nautobot_ssot_servicenow/third_party/pysnow/params_builder.py
nautobot_ssot_servicenow/third_party/pysnow/query_builder.py
nautobot_ssot_servicenow/third_party/pysnow/request.py
nautobot_ssot_servicenow/third_party/pysnow/resource.py
nautobot_ssot_servicenow/third_party/pysnow/response.py
nautobot_ssot_servicenow/third_party/pysnow/url_builder.py
nautobot_ssot_servicenow/urls.py
nautobot_ssot_servicenow/utils.py
nautobot_ssot_servicenow/views.py
nautobot_ssot_servicenow-0.9.2.dist-info/LICENSE
nautobot_ssot_servicenow-0.9.2.dist-info/WHEEL
nautobot_ssot_servicenow-0.9.2.dist-info/METADATA
nautobot_ssot_servicenow-0.9.2.dist-info/RECORD
