Metadata-Version: 2.1
Name: nautobot-ssot-servicenow
Version: 0.9.2
Summary: Nautobot SSoT ServiceNow
Home-page: https://github.com/nautobot/nautobot-plugin-ssot-servicenow
License: Apache-2.0
Keywords: nautobot,nautobot-plugin
Author: Network to Code, LLC
Author-email: opensource@networktocode.com
Requires-Python: >=3.7,<4.0
Classifier: License :: OSI Approved :: Apache Software License
Classifier: Programming Language :: Python :: 3
Classifier: Programming Language :: Python :: 3.10
Classifier: Programming Language :: Python :: 3.7
Classifier: Programming Language :: Python :: 3.8
Classifier: Programming Language :: Python :: 3.9
Requires-Dist: Jinja2 (>=2.11.3)
Requires-Dist: PyYAML (>=5.4)
Requires-Dist: diffsync (>=1.3.0,<2.0.0)
Requires-Dist: ijson (>=2.5.1,<3.0.0)
Requires-Dist: nautobot (>=1.2.0,<2.0.0)
Requires-Dist: nautobot-ssot (>=1.0.1,<2.0.0)
Requires-Dist: oauthlib (>=3.1.0,<4.0.0)
Requires-Dist: python-magic (>=0.4.15,<0.5.0)
Requires-Dist: pytz (>=2019.3)
Requires-Dist: requests (>=2.21.0,<3.0.0)
Requires-Dist: requests-oauthlib (>=1.3.0,<2.0.0)
Requires-Dist: six (>=1.13.0,<2.0.0)
Project-URL: Repository, https://github.com/nautobot/nautobot-plugin-ssot-servicenow
